identity_ocr/__init__.py
identity_ocr/core.py
identity_ocr/fulltext.py
identity_ocr/image.py
identity_ocr/mrz.py
identity_ocr/utils.py
identity_ocr-0.1.14.dist-info/METADATA
identity_ocr-0.1.14.dist-info/WHEEL
identity_ocr-0.1.14.dist-info/top_level.txt
identity_ocr-0.1.14.dist-info/RECORD
