Metadata-Version: 2.4
Name: identity-ocr
Version: 0.1.14
Summary: A robust Python library for extracting information from passports using OCR (Tesseract) and MRZ parsing.
License: MIT
Classifier: Development Status :: 3 - Alpha
Classifier: Intended Audience :: Developers
Classifier: License :: OSI Approved :: MIT License
Classifier: Programming Language :: Python :: 3
Classifier: Programming Language :: Python :: 3.7
Classifier: Programming Language :: Python :: 3.8
Classifier: Programming Language :: Python :: 3.9
Classifier: Programming Language :: Python :: 3.10
Classifier: Programming Language :: Python :: 3.11
Classifier: Programming Language :: Python :: 3.12
Classifier: Programming Language :: Python :: 3.13
Requires-Python: >=3.7
Requires-Dist: pytesseract
Requires-Dist: opencv-python-headless
Requires-Dist: mrz
Requires-Dist: numpy
Dynamic: requires-python
